[{"name":"coat/0000.png","x":0,"y":0},{"name":"coat/0300.png","x":-28,"y":0},{"name":"coat/0301.png","x":-56,"y":0},{"name":"coat/0302.png","x":-84,"y":0},{"name":"coat/0303.png","x":-112,"y":0},{"name":"coat/0600.png","x":-140,"y":0},{"name":"coat/0601.png","x":-168,"y":0},{"name":"coat/0602.png","x":-196,"y":0},{"name":"coat/0603.png","x":-224,"y":0},{"name":"coat/0700.png","x":-252,"y":0},{"name":"coat/0701.png","x":-280,"y":0},{"name":"coat/0702.png","x":-308,"y":0},{"name":"coat/0703.png","x":-336,"y":0},{"name":"coat/0800.png","x":-364,"y":0},{"name":"coat/0801.png","x":-392,"y":0},{"name":"coat/0802.png","x":-420,"y":0},{"name":"coat/0803.png","x":0,"y":-28},{"name":"coat/0900.png","x":-28,"y":-28},{"name":"coat/0901.png","x":-56,"y":-28},{"name":"coat/0902.png","x":-84,"y":-28},{"name":"coat/10000.png","x":-112,"y":-28},{"name":"coat/10100.png","x":-140,"y":-28},{"name":"coat/10200.png","x":-168,"y":-28},{"name":"coat/10700.png","x":-196,"y":-28},{"name":"coat/10701.png","x":-224,"y":-28},{"name":"coat/10702.png","x":-252,"y":-28},{"name":"coat/10703.png","x":-280,"y":-28},{"name":"coat/10800.png","x":-308,"y":-28},{"name":"coat/10801.png","x":-336,"y":-28},{"name":"coat/10802.png","x":-364,"y":-28},{"name":"coat/10803.png","x":-392,"y":-28},{"name":"coat/10900.png","x":-420,"y":-28},{"name":"coat/10901.png","x":0,"y":-56},{"name":"coat/10902.png","x":-28,"y":-56},{"name":"coat/10903.png","x":-56,"y":-56},{"name":"coat/11000.png","x":-84,"y":-56},{"name":"coat/11001.png","x":-112,"y":-56},{"name":"coat/11004.png","x":-140,"y":-56},{"name":"coat/11100.png","x":-168,"y":-56},{"name":"coat/11101.png","x":-196,"y":-56},{"name":"coat/11102.png","x":-224,"y":-56},{"name":"coat/11103.png","x":-252,"y":-56},{"name":"coat/11200.png","x":-280,"y":-56},{"name":"coat/11201.png","x":-308,"y":-56},{"name":"coat/11202.png","x":-336,"y":-56},{"name":"coat/11203.png","x":-364,"y":-56},{"name":"coat/11600.png","x":-392,"y":-56},{"name":"coat/11602.png","x":-420,"y":-56},{"name":"coat/11700.png","x":0,"y":-84},{"name":"coat/11701.png","x":-28,"y":-84},{"name":"coat/11702.png","x":-56,"y":-84},{"name":"coat/11703.png","x":-84,"y":-84},{"name":"coat/11800.png","x":-112,"y":-84},{"name":"coat/11801.png","x":-140,"y":-84},{"name":"coat/11802.png","x":-168,"y":-84},{"name":"coat/11803.png","x":-196,"y":-84},{"name":"coat/1203.png","x":-224,"y":-84},{"name":"coat/1300.png","x":-252,"y":-84},{"name":"coat/13000.png","x":-280,"y":-84},{"name":"coat/1301.png","x":-308,"y":-84},{"name":"coat/13200.png","x":-336,"y":-84},{"name":"coat/13201.png","x":-364,"y":-84},{"name":"coat/13202.png","x":-392,"y":-84},{"name":"coat/13203.png","x":-420,"y":-84},{"name":"coat/13300.png","x":0,"y":-112},{"name":"coat/13301.png","x":-28,"y":-112},{"name":"coat/13302.png","x":-56,"y":-112},{"name":"coat/13303.png","x":-84,"y":-112},{"name":"coat/13304.png","x":-112,"y":-112},{"name":"coat/13305.png","x":-140,"y":-112},{"name":"coat/13500.png","x":-168,"y":-112},{"name":"coat/13501.png","x":-196,"y":-112},{"name":"coat/13502.png","x":-224,"y":-112},{"name":"coat/13503.png","x":-252,"y":-112},{"name":"coat/1500.png","x":-280,"y":-112},{"name":"coat/1501.png","x":-308,"y":-112},{"name":"coat/1502.png","x":-336,"y":-112},{"name":"coat/1600.png","x":-364,"y":-112},{"name":"coat/1601.png","x":-392,"y":-112},{"name":"coat/1602.png","x":-420,"y":-112},{"name":"coat/1603.png","x":0,"y":-140},{"name":"coat/1700.png","x":-28,"y":-140},{"name":"coat/1900.png","x":-56,"y":-140},{"name":"coat/1901.png","x":-84,"y":-140},{"name":"coat/1902.png","x":-112,"y":-140},{"name":"coat/1903.png","x":-140,"y":-140},{"name":"coat/2000.png","x":-168,"y":-140},{"name":"coat/2001.png","x":-196,"y":-140},{"name":"coat/2002.png","x":-224,"y":-140},{"name":"coat/2003.png","x":-252,"y":-140},{"name":"coat/2100.png","x":-280,"y":-140},{"name":"coat/2101.png","x":-308,"y":-140},{"name":"coat/2102.png","x":-336,"y":-140},{"name":"coat/2103.png","x":-364,"y":-140},{"name":"coat/2200.png","x":-392,"y":-140},{"name":"coat/2201.png","x":-420,"y":-140},{"name":"coat/2202.png","x":0,"y":-168},{"name":"coat/2203.png","x":-28,"y":-168},{"name":"coat/2300.png","x":-56,"y":-168},{"name":"coat/2301.png","x":-84,"y":-168},{"name":"coat/2400.png","x":-112,"y":-168},{"name":"coat/2402.png","x":-140,"y":-168},{"name":"coat/2500.png","x":-168,"y":-168},{"name":"coat/2501.png","x":-196,"y":-168},{"name":"coat/2502.png","x":-224,"y":-168},{"name":"coat/2600.png","x":-252,"y":-168},{"name":"coat/2601.png","x":-280,"y":-168},{"name":"coat/2602.png","x":-308,"y":-168},{"name":"coat/2603.png","x":-336,"y":-168},{"name":"coat/2700.png","x":-364,"y":-168},{"name":"coat/2701.png","x":-392,"y":-168},{"name":"coat/2800.png","x":-420,"y":-168},{"name":"coat/3100.png","x":0,"y":-196},{"name":"coat/3101.png","x":-28,"y":-196},{"name":"coat/3700.png","x":-56,"y":-196},{"name":"coat/3701.png","x":-84,"y":-196},{"name":"coat/3900.png","x":-112,"y":-196},{"name":"coat/3901.png","x":-140,"y":-196},{"name":"coat/3902.png","x":-168,"y":-196},{"name":"coat/3903.png","x":-196,"y":-196},{"name":"coat/4000.png","x":-224,"y":-196},{"name":"coat/4002.png","x":-252,"y":-196},{"name":"coat/4004.png","x":-280,"y":-196},{"name":"coat/4005.png","x":-308,"y":-196},{"name":"coat/4100.png","x":-336,"y":-196},{"name":"coat/4300.png","x":-364,"y":-196},{"name":"coat/4301.png","x":-392,"y":-196},{"name":"coat/4302.png","x":-420,"y":-196},{"name":"coat/4303.png","x":0,"y":-224},{"name":"coat/4400.png","x":-28,"y":-224},{"name":"coat/4401.png","x":-56,"y":-224},{"name":"coat/4500.png","x":-84,"y":-224},{"name":"coat/4501.png","x":-112,"y":-224},{"name":"coat/4502.png","x":-140,"y":-224},{"name":"coat/4503.png","x":-168,"y":-224},{"name":"coat/4800.png","x":-196,"y":-224},{"name":"coat/4801.png","x":-224,"y":-224},{"name":"coat/4802.png","x":-252,"y":-224},{"name":"coat/4803.png","x":-280,"y":-224},{"name":"coat/4900.png","x":-308,"y":-224},{"name":"coat/5100.png","x":-336,"y":-224},{"name":"coat/5101.png","x":-364,"y":-224},{"name":"coat/5102.png","x":-392,"y":-224},{"name":"coat/5103.png","x":-420,"y":-224},{"name":"coat/5200.png","x":0,"y":-252},{"name":"coat/5300.png","x":-28,"y":-252},{"name":"coat/5400.png","x":-56,"y":-252},{"name":"coat/5401.png","x":-84,"y":-252},{"name":"coat/5402.png","x":-112,"y":-252},{"name":"coat/5403.png","x":-140,"y":-252},{"name":"coat/5500.png","x":-168,"y":-252},{"name":"coat/5501.png","x":-196,"y":-252},{"name":"coat/5700.png","x":-224,"y":-252},{"name":"coat/5701.png","x":-252,"y":-252},{"name":"coat/5800.png","x":-280,"y":-252},{"name":"coat/5801.png","x":-308,"y":-252},{"name":"coat/6000.png","x":-336,"y":-252},{"name":"coat/6001.png","x":-364,"y":-252},{"name":"coat/6002.png","x":-392,"y":-252},{"name":"coat/6003.png","x":-420,"y":-252},{"name":"coat/6100.png","x":0,"y":-280},{"name":"coat/6101.png","x":-28,"y":-280},{"name":"coat/6102.png","x":-56,"y":-280},{"name":"coat/6103.png","x":-84,"y":-280},{"name":"coat/6200.png","x":-112,"y":-280},{"name":"coat/6201.png","x":-140,"y":-280},{"name":"coat/6202.png","x":-168,"y":-280},{"name":"coat/6203.png","x":-196,"y":-280},{"name":"coat/6300.png","x":-224,"y":-280},{"name":"coat/6301.png","x":-252,"y":-280},{"name":"coat/6302.png","x":-280,"y":-280},{"name":"coat/6400.png","x":-308,"y":-280},{"name":"coat/6401.png","x":-336,"y":-280},{"name":"coat/6402.png","x":-364,"y":-280},{"name":"coat/6800.png","x":-392,"y":-280},{"name":"coat/6900.png","x":-420,"y":-280},{"name":"coat/6901.png","x":0,"y":-308},{"name":"coat/6902.png","x":-28,"y":-308},{"name":"coat/6903.png","x":-56,"y":-308},{"name":"coat/7000.png","x":-84,"y":-308},{"name":"coat/7001.png","x":-112,"y":-308},{"name":"coat/7100.png","x":-140,"y":-308},{"name":"coat/7101.png","x":-168,"y":-308},{"name":"coat/7102.png","x":-196,"y":-308},{"name":"coat/7103.png","x":-224,"y":-308},{"name":"coat/7300.png","x":-252,"y":-308},{"name":"coat/7301.png","x":-280,"y":-308},{"name":"coat/7302.png","x":-308,"y":-308},{"name":"coat/7303.png","x":-336,"y":-308},{"name":"coat/7600.png","x":-364,"y":-308},{"name":"coat/7601.png","x":-392,"y":-308},{"name":"coat/7602.png","x":-420,"y":-308},{"name":"coat/7900.png","x":0,"y":-336},{"name":"coat/7901.png","x":-28,"y":-336},{"name":"coat/7902.png","x":-56,"y":-336},{"name":"coat/8000.png","x":-84,"y":-336},{"name":"coat/8001.png","x":-112,"y":-336},{"name":"coat/8002.png","x":-140,"y":-336},{"name":"coat/8100.png","x":-168,"y":-336},{"name":"coat/8101.png","x":-196,"y":-336},{"name":"coat/8102.png","x":-224,"y":-336},{"name":"coat/8103.png","x":-252,"y":-336},{"name":"coat/8200.png","x":-280,"y":-336},{"name":"coat/8201.png","x":-308,"y":-336},{"name":"coat/8202.png","x":-336,"y":-336},{"name":"coat/8203.png","x":-364,"y":-336},{"name":"coat/8300.png","x":-392,"y":-336},{"name":"coat/8301.png","x":-420,"y":-336},{"name":"coat/8302.png","x":0,"y":-364},{"name":"coat/8500.png","x":-28,"y":-364},{"name":"coat/8800.png","x":-56,"y":-364},{"name":"coat/8801.png","x":-84,"y":-364},{"name":"coat/8802.png","x":-112,"y":-364},{"name":"coat/8803.png","x":-140,"y":-364},{"name":"coat/9200.png","x":-168,"y":-364},{"name":"coat/9201.png","x":-196,"y":-364},{"name":"coat/9300.png","x":-224,"y":-364},{"name":"coat/9301.png","x":-252,"y":-364},{"name":"coat/9302.png","x":-280,"y":-364},{"name":"coat/9400.png","x":-308,"y":-364},{"name":"coat/9401.png","x":-336,"y":-364},{"name":"coat/9402.png","x":-364,"y":-364},{"name":"coat/9403.png","x":-392,"y":-364},{"name":"coat/9500.png","x":-420,"y":-364},{"name":"coat/9501.png","x":0,"y":-392},{"name":"coat/9502.png","x":-28,"y":-392},{"name":"coat/9503.png","x":-56,"y":-392},{"name":"coat/9800.png","x":-84,"y":-392},{"name":"coat/9801.png","x":-112,"y":-392},{"name":"coat/9802.png","x":-140,"y":-392},{"name":"coat/9803.png","x":-168,"y":-392}]