[{"name":"coat/0000.png","x":0,"y":0},{"name":"coat/0100.png","x":-28,"y":0},{"name":"coat/0101.png","x":-56,"y":0},{"name":"coat/0102.png","x":-84,"y":0},{"name":"coat/0103.png","x":-112,"y":0},{"name":"coat/0200.png","x":-140,"y":0},{"name":"coat/0201.png","x":-168,"y":0},{"name":"coat/0202.png","x":-196,"y":0},{"name":"coat/0203.png","x":-224,"y":0},{"name":"coat/0300.png","x":-252,"y":0},{"name":"coat/0301.png","x":-280,"y":0},{"name":"coat/0400.png","x":-308,"y":0},{"name":"coat/0401.png","x":0,"y":-28},{"name":"coat/0402.png","x":-28,"y":-28},{"name":"coat/0403.png","x":-56,"y":-28},{"name":"coat/0500.png","x":-84,"y":-28},{"name":"coat/0501.png","x":-112,"y":-28},{"name":"coat/0502.png","x":-140,"y":-28},{"name":"coat/0503.png","x":-168,"y":-28},{"name":"coat/0600.png","x":-196,"y":-28},{"name":"coat/0601.png","x":-224,"y":-28},{"name":"coat/0602.png","x":-252,"y":-28},{"name":"coat/0603.png","x":-280,"y":-28},{"name":"coat/0700.png","x":-308,"y":-28},{"name":"coat/0701.png","x":0,"y":-56},{"name":"coat/0702.png","x":-28,"y":-56},{"name":"coat/0703.png","x":-56,"y":-56},{"name":"coat/0800.png","x":-84,"y":-56},{"name":"coat/0801.png","x":-112,"y":-56},{"name":"coat/0802.png","x":-140,"y":-56},{"name":"coat/1000.png","x":-168,"y":-56},{"name":"coat/1001.png","x":-196,"y":-56},{"name":"coat/1002.png","x":-224,"y":-56},{"name":"coat/1100.png","x":-252,"y":-56},{"name":"coat/1101.png","x":-280,"y":-56},{"name":"coat/1200.png","x":-308,"y":-56},{"name":"coat/1201.png","x":0,"y":-84},{"name":"coat/1202.png","x":-28,"y":-84},{"name":"coat/1300.png","x":-56,"y":-84},{"name":"coat/1301.png","x":-84,"y":-84},{"name":"coat/1302.png","x":-112,"y":-84},{"name":"coat/1303.png","x":-140,"y":-84},{"name":"coat/1400.png","x":-168,"y":-84},{"name":"coat/1401.png","x":-196,"y":-84},{"name":"coat/1402.png","x":-224,"y":-84},{"name":"coat/1403.png","x":-252,"y":-84},{"name":"coat/1500.png","x":-280,"y":-84},{"name":"coat/1501.png","x":-308,"y":-84},{"name":"coat/1502.png","x":0,"y":-112},{"name":"coat/1600.png","x":-28,"y":-112},{"name":"coat/1601.png","x":-56,"y":-112},{"name":"coat/1602.png","x":-84,"y":-112},{"name":"coat/1603.png","x":-112,"y":-112},{"name":"coat/1900.png","x":-140,"y":-112},{"name":"coat/1901.png","x":-168,"y":-112},{"name":"coat/1902.png","x":-196,"y":-112},{"name":"coat/2100.png","x":-224,"y":-112},{"name":"coat/2101.png","x":-252,"y":-112},{"name":"coat/2102.png","x":-280,"y":-112},{"name":"coat/2103.png","x":-308,"y":-112},{"name":"coat/2200.png","x":0,"y":-140},{"name":"coat/2201.png","x":-28,"y":-140},{"name":"coat/2202.png","x":-56,"y":-140},{"name":"coat/2203.png","x":-84,"y":-140},{"name":"coat/2400.png","x":-112,"y":-140},{"name":"coat/2401.png","x":-140,"y":-140},{"name":"coat/2402.png","x":-168,"y":-140},{"name":"coat/2403.png","x":-196,"y":-140},{"name":"coat/2500.png","x":-224,"y":-140},{"name":"coat/2501.png","x":-252,"y":-140},{"name":"coat/2502.png","x":-280,"y":-140},{"name":"coat/2702.png","x":-308,"y":-140},{"name":"coat/2703.png","x":0,"y":-168},{"name":"coat/2704.png","x":-28,"y":-168},{"name":"coat/2800.png","x":-56,"y":-168},{"name":"coat/2801.png","x":-84,"y":-168},{"name":"coat/2802.png","x":-112,"y":-168},{"name":"coat/2803.png","x":-140,"y":-168},{"name":"coat/3000.png","x":-168,"y":-168},{"name":"coat/3001.png","x":-196,"y":-168},{"name":"coat/3002.png","x":-224,"y":-168},{"name":"coat/3003.png","x":-252,"y":-168},{"name":"coat/3100.png","x":-280,"y":-168},{"name":"coat/3101.png","x":-308,"y":-168},{"name":"coat/3102.png","x":0,"y":-196},{"name":"coat/3103.png","x":-28,"y":-196},{"name":"coat/3200.png","x":-56,"y":-196},{"name":"coat/3300.png","x":-84,"y":-196},{"name":"coat/3301.png","x":-112,"y":-196},{"name":"coat/3302.png","x":-140,"y":-196},{"name":"coat/3303.png","x":-168,"y":-196},{"name":"coat/3400.png","x":-196,"y":-196},{"name":"coat/3401.png","x":-224,"y":-196},{"name":"coat/3404.png","x":-252,"y":-196},{"name":"coat/3500.png","x":-280,"y":-196},{"name":"coat/3501.png","x":-308,"y":-196},{"name":"coat/3502.png","x":0,"y":-224},{"name":"coat/3503.png","x":-28,"y":-224},{"name":"coat/3700.png","x":-56,"y":-224},{"name":"coat/3701.png","x":-84,"y":-224},{"name":"coat/3702.png","x":-112,"y":-224},{"name":"coat/3703.png","x":-140,"y":-224},{"name":"coat/3800.png","x":-168,"y":-224},{"name":"coat/3801.png","x":-196,"y":-224},{"name":"coat/3802.png","x":-224,"y":-224},{"name":"coat/3803.png","x":-252,"y":-224},{"name":"coat/3900.png","x":-280,"y":-224},{"name":"coat/3901.png","x":-308,"y":-224},{"name":"coat/3902.png","x":0,"y":-252},{"name":"coat/3903.png","x":-28,"y":-252},{"name":"coat/4200.png","x":-56,"y":-252},{"name":"coat/4202.png","x":-84,"y":-252},{"name":"coat/4300.png","x":-112,"y":-252},{"name":"coat/4301.png","x":-140,"y":-252},{"name":"coat/4302.png","x":-168,"y":-252},{"name":"coat/4303.png","x":-196,"y":-252},{"name":"coat/4400.png","x":-224,"y":-252},{"name":"coat/4401.png","x":-252,"y":-252},{"name":"coat/4402.png","x":-280,"y":-252},{"name":"coat/4403.png","x":-308,"y":-252},{"name":"coat/5800.png","x":0,"y":-280},{"name":"coat/6000.png","x":-28,"y":-280},{"name":"coat/6001.png","x":-56,"y":-280},{"name":"coat/6002.png","x":-84,"y":-280},{"name":"coat/6003.png","x":-112,"y":-280},{"name":"coat/7000.png","x":-140,"y":-280},{"name":"coat/7001.png","x":-168,"y":-280},{"name":"coat/7002.png","x":-196,"y":-280},{"name":"coat/7003.png","x":-224,"y":-280},{"name":"coat/8900.png","x":-252,"y":-280},{"name":"coat/8901.png","x":-280,"y":-280},{"name":"coat/8902.png","x":-308,"y":-280},{"name":"coat/8903.png","x":0,"y":-308},{"name":"coat/8904.png","x":-28,"y":-308},{"name":"coat/8905.png","x":-56,"y":-308}]